MANIFEST.in
setup.cfg
setup.py
systax/__init__.py
systax/exceptions.py
systax/geometry.py
systax/symmetry.py
systax.egg-info/PKG-INFO
systax.egg-info/SOURCES.txt
systax.egg-info/dependency_links.txt
systax.egg-info/requires.txt
systax.egg-info/top_level.txt
systax/analysis/__init__.py
systax/analysis/analyzer.py
systax/analysis/class1danalyzer.py
systax/analysis/class2danalyzer.py
systax/analysis/class3danalyzer.py
systax/analysis/symmetryanalyzer.py
systax/classification/__init__.py
systax/classification/classifications.py
systax/classification/classifier.py
systax/classification/periodicfinder.py
systax/core/__init__.py
systax/core/lattice.py
systax/core/linkedunits.py
systax/core/system.py
systax/data/__init__.py
systax/data/alphabet_data.py
systax/data/constants.py
systax/data/element_data.py
systax/data/symmetry_data.py
systax/utils/__init__.py
systax/utils/segfault_protect.py