Metadata-Version: 1.2
Name: systax
Version: 0.1.3
Summary: WARNING: This package has been renamed to MatID: https://singroup.github.io/matid/
Home-page: UNKNOWN
Author: Lauri Himanen
Author-email: lauri.himanen@aalto.fi
License: Apache License 2.0
Keywords: atoms structure materials science crystal symmetry
Platform: UNKNOWN
Classifier: Development Status :: 4 - Beta
Classifier: Intended Audience :: Developers
Classifier: Topic :: Scientific/Engineering :: Physics
Classifier: License :: OSI Approved :: Apache Software License
Classifier: Programming Language :: Python :: 2
Classifier: Programming Language :: Python :: 2.6
Classifier: Programming Language :: Python :: 2.7
Classifier: Programming Language :: Python :: 3
Classifier: Programming Language :: Python :: 3.2
Classifier: Programming Language :: Python :: 3.3
Classifier: Programming Language :: Python :: 3.4
Classifier: Programming Language :: Python :: 3.5
Requires-Python: >=2.6, <4
